public class exercises01.TestLongCounterExperiments {
  exercises01.TestLongCounterExperiments$LongCounter lc;

  int counts;

  public exercises01.TestLongCounterExperiments();
    Code:
       0: aload_0
       1: invokespecial #1                  // Method java/lang/Object."<init>":()V
       4: aload_0
       5: new           #2                  // class exercises01/TestLongCounterExperiments$LongCounter
       8: dup
       9: aload_0
      10: invokespecial #3                  // Method exercises01/TestLongCounterExperiments$LongCounter."<init>":(Lexercises01/TestLongCounterExperiments;)V
      13: putfield      #4                  // Field lc:Lexercises01/TestLongCounterExperiments$LongCounter;
      16: aload_0
      17: ldc           #5                  // int 10000000
      19: putfield      #6                  // Field counts:I
      22: new           #7                  // class java/lang/Thread
      25: dup
      26: aload_0
      27: invokedynamic #8,  0              // InvokeDynamic #0:run:(Lexercises01/TestLongCounterExperiments;)Ljava/lang/Runnable;
      32: invokespecial #9                  // Method java/lang/Thread."<init>":(Ljava/lang/Runnable;)V
      35: astore_1
      36: new           #7                  // class java/lang/Thread
      39: dup
      40: aload_0
      41: invokedynamic #10,  0             // InvokeDynamic #1:run:(Lexercises01/TestLongCounterExperiments;)Ljava/lang/Runnable;
      46: invokespecial #9                  // Method java/lang/Thread."<init>":(Ljava/lang/Runnable;)V
      49: astore_2
      50: aload_1
      51: invokevirtual #11                 // Method java/lang/Thread.start:()V
      54: aload_2
      55: invokevirtual #11                 // Method java/lang/Thread.start:()V
      58: aload_1
      59: invokevirtual #12                 // Method java/lang/Thread.join:()V
      62: aload_2
      63: invokevirtual #12                 // Method java/lang/Thread.join:()V
      66: goto          78
      69: astore_3
      70: getstatic     #14                 // Field java/lang/System.out:Ljava/io/PrintStream;
      73: ldc           #15                 // String Some thread was interrupted
      75: invokevirtual #16                 // Method java/io/PrintStream.println:(Ljava/lang/String;)V
      78: getstatic     #14                 // Field java/lang/System.out:Ljava/io/PrintStream;
      81: new           #17                 // class java/lang/StringBuilder
      84: dup
      85: invokespecial #18                 // Method java/lang/StringBuilder."<init>":()V
      88: ldc           #19                 // String Count is
      90: invokevirtual #20                 // Method java/lang/StringBuilder.append:(Ljava/lang/String;)Ljava/lang/StringBuilder;
      93: aload_0
      94: getfield      #4                  // Field lc:Lexercises01/TestLongCounterExperiments$LongCounter;
      97: invokevirtual #21                 // Method exercises01/TestLongCounterExperiments$LongCounter.get:()J
     100: invokevirtual #22                 // Method java/lang/StringBuilder.append:(J)Ljava/lang/StringBuilder;
     103: ldc           #23                 // String  and should be
     105: invokevirtual #20                 // Method java/lang/StringBuilder.append:(Ljava/lang/String;)Ljava/lang/StringBuilder;
     108: iconst_2
     109: aload_0
     110: getfield      #6                  // Field counts:I
     113: imul
     114: invokevirtual #24                 // Method java/lang/StringBuilder.append:(I)Ljava/lang/StringBuilder;
     117: invokevirtual #25                 // Method java/lang/StringBuilder.toString:()Ljava/lang/String;
     120: invokevirtual #16                 // Method java/io/PrintStream.println:(Ljava/lang/String;)V
     123: return
    Exception table:
       from    to  target type
          58    66    69   Class java/lang/InterruptedException

  public static void main(java.lang.String[]);
    Code:
       0: new           #26                 // class exercises01/TestLongCounterExperiments
       3: dup
       4: invokespecial #27                 // Method "<init>":()V
       7: pop
       8: return
}
